scaleup_bo/__init__.py
scaleup_bo/kernel.py
scaleup_bo/plots.py
scaleup_bo/scale.py
scaleup_bo/utils.py
scaleup_bo/acquisition_functions/__init__.py
scaleup_bo/acquisition_functions/base.py
scaleup_bo/acquisition_functions/expected_improvement.py
scaleup_bo/acquisition_functions/probability_of_improvement.py
scaleup_bo/acquisition_functions/upper_confidence_bound.py
scaleup_bo/optimizers/__init__.py
scaleup_bo/optimizers/base.py
scaleup_bo/optimizers/large_scale_opt.py
scaleup_bo/optimizers/small_scale_opt.py
scaleup_bo/surrogate_models/__init__.py
scaleup_bo/surrogate_models/base.py
scaleup_bo/surrogate_models/large_scale_gp.py
scaleup_bo/surrogate_models/small_scale_gp.py
scaleup_bo/tests/__init__.py
scaleup_bo/tests/test_acquisition_ei.py
scaleup_bo/tests/test_acquisition_pi.py
scaleup_bo/tests/test_acquisition_ucb.py
scaleup_bo/tests/test_kernel.py
scaleup_bo/tests/test_large_scale_gp.py
scaleup_bo/tests/test_large_scale_opt.py
scaleup_bo/tests/test_optimizer.py
scaleup_bo/tests/test_plots.py
scaleup_bo/tests/test_scale.py
scaleup_bo/tests/test_small_scale_gp.py
scaleup_bo/tests/test_small_scale_opt.py
scaleup_bo/tests/test_utils.py
scaleup_optimizers-1.0.6.dist-info/LICENSE
scaleup_optimizers-1.0.6.dist-info/METADATA
scaleup_optimizers-1.0.6.dist-info/WHEEL
scaleup_optimizers-1.0.6.dist-info/top_level.txt
scaleup_optimizers-1.0.6.dist-info/RECORD
